{
	"WBUI2": {
		"settings": {
			"OpenButton": 2,
			"HideIcon": true,
			"HideIconAfter": 60,
			"IconURL": "",
			"DisableIconText": true,
			"IconPosition": 2,
			"IconTextColor": 7,
			"OpenOnStart": true,
			"OpenOnStartOnlyNewPlayers": true,
			"UpdateInterval": 6
		},
		"tabs": [
			{
				"tab1": {
					"layout": 1,
					"buttontext": "<RichColor Color=\"0,1,1,1\">Welcome</>",
					"title1": "",
					"text1": "",
					"imageurl": "https://i.postimg.cc/Gmy0gMgf/Startbild-Island.png"
				}
			},
			{
				"tab2": {
					"layout": 1,
					"buttontext": "<RichColor Color=\"0,1,1,1\">Shop</>",
					"title1": "",
					"text1": "",
					"imageurl": "https://i.postimg.cc/ydrDW1Gs/Ressourcen-Shop.png"
				}
			},
			{
				"tab3": {
					"layout": 1,
					"buttontext": "<RichColor Color=\"0,1,1,1\">Shop2</>",
					"title1": "",
					"text1": "",
					"imageurl": "https://i.postimg.cc/L5YnPddf/Kits-Sell-Shop-Pv-E.png"
				}
			},
			{
				"tab4": {
					"layout": 1,
					"buttontext": "<RichColor Color=\"0,1,1,1\">Shop3</>",
					"title1": "",
					"text1": "",
					"imageurl": "https://i.postimg.cc/yYcSNtYg/Gamble-Shop.png"
				}
			},
			{
				"tab5": {
					"layout": 1,
					"buttontext": "<RichColor Color=\"0,1,1,1\">Commands</>",
					"title1": "",
					"text1": "",
					"imageurl": "https://i.postimg.cc/N0gGBP5c/Commands.png"
				}
			},
			{
				"tab6": {
					"layout": 1,
					"buttontext": "<RichColor Color=\"0,1,1,1\">Events</>",
					"title1": "",
					"text1": "",
					"imageurl": "https://i.postimg.cc/XY2nQQhy/Bosse-Events.png"
				}
			},
			{
				"tab7": {
					"layout": 1,
					"buttontext": "<RichColor Color=\"0,1,1,1\">Settings|Rules</>",
					"title1": "",
					"text1": "",
					"imageurl": "https://i.postimg.cc/T32H2THg/Settings-Rules-Pv-E.png"
				}
			}
		],
		"links": [
			{
				"link1": {
					"text": "<RichColor Color=\"1,0,0,1\">Trailer video</>",
					"url": "https://www.youtube.com/watch?v=NHinLwUdhxc"
				}
			},
			{
				"link2": {
					"text": "<RichColor Color=\"0,1,0,1\">Discord</>",
					"url": "https://discord.gg/TZPbvsVm2U"
				}
			},
			{
				"link3": {
					"text": "<RichColor Color=\"1,0,0,1\">Youtube[GER]</>",
					"url": "https://www.youtube.com/@RtRFinch/videos"
				}
			},
			{
				"link4": {
					"text": "<RichColor Color=\"1,0,0,1\">Youtube[EN]</>",
					"url": "https://www.youtube.com/@realdodofrodo/videos"
				}
			},
			{
				"link5": {
					"text": "<RichColor Color=\"0,1,1,1\">Dododex</>",
					"url": "https://www.dododex.com/"
				}
			},
			{
				"link6": {
					"text": "<RichColor Color=\"0,1,1,1\">RTR Website</>",
					"url": "https://rtrark.org/"
				}
			}
		]
	}
}